{"id": "382", "iri": "382", "baseIri": "382", "instances": "382", "attributes": "382", "label_IRI-based": "OBI_0000278", "label_en": "disease stage", "annotations": {"definition": [{"identifier": "IAO_0000115", "language": "en", "value": "a part of an occurrence of a disease process which is associated with position in the normal progression of the disease", "type": "label"}], "imported from": [{"identifier": "IAO_0000412", "language": "undefined", "value": "http://purl.obolibrary.org/obo/obi.owl", "type": "iri"}]}, "superClasses": ["170"], "subClasses": ["574", "639", "643", "648", "652"], "name": "disease stage", "body": "a part of an occurrence of a disease process which is associated with position in the normal progression of the disease", "children": [{"id": "639", "iri": "639", "baseIri": "639", "instances": "639", "attributes": "639", "label_IRI-based": "OGMS_0000105", "label_en": "relapse", "annotations": {"date": [{"identifier": "date", "language": "undefined", "value": "10 NOV 2015", "type": "label"}], "definition": [{"identifier": "IAO_0000115", "language": "undefined", "value": "A disease stage which is preceded by a remission and characterized by the return of a manifestation of a disease.", "type": "label"}], "term editor": [{"identifier": "IAO_0000117", "language": "undefined", "value": "Albert Goldfain\nRichard Scheuermann\nSagar Jain", "type": "label"}], "editor note": [{"identifier": "IAO_0000116", "language": "en", "value": "A pathological bodily process which is part of a disease couse that occurs after an incomplete remission and that is similar to earlier parts of the disease course.", "type": "label"}], "definition source": [{"identifier": "IAO_0000119", "language": "undefined", "value": "http://code.google.com/p/ogms/issues/detail?id=73", "type": "label"}], "alternative term": [{"identifier": "IAO_0000118", "language": "undefined", "value": "recurrent", "type": "label"}]}, "superClasses": ["382"], "subClasses": null, "name": "relapse", "body": "A disease stage which is preceded by a remission and characterized by the return of a manifestation of a disease."}, {"id": "643", "iri": "643", "baseIri": "643", "instances": "643", "attributes": "643", "label_IRI-based": "OGMS_0000106", "label_en": "remission", "annotations": {"date": [{"identifier": "date", "language": "undefined", "value": "10 NOV 2015", "type": "label"}], "definition": [{"identifier": "IAO_0000115", "language": "undefined", "value": "A disease stage which is characterized by the lack of a manifestation of a disease", "type": "label"}], "term editor": [{"identifier": "IAO_0000117", "language": "undefined", "value": "Albert Goldfain\nRichard Scheuermann\nSagar Jain", "type": "label"}], "editor note": [{"identifier": "IAO_0000116", "language": "en", "value": "A part of a disease course in which the extent or rate of change of the signs and symptoms of a disorder has decreased.", "type": "label"}], "definition source": [{"identifier": "IAO_0000119", "language": "undefined", "value": "http://code.google.com/p/ogms/issues/detail?id=73", "type": "label"}]}, "superClasses": ["382"], "subClasses": ["1366", "1369"], "name": "remission", "body": "A disease stage which is characterized by the lack of a manifestation of a disease", "children": [{"id": "1366", "iri": "1366", "baseIri": "1366", "instances": "1366", "attributes": "1366", "label_IRI-based": "OGMS_0000120", "label_en": "complete remission", "annotations": {"definition": [{"identifier": "IAO_0000115", "language": "undefined", "value": "A remission which is characterized by a prolonged lack of all manifestations of a disease", "type": "label"}]}, "superClasses": ["643"], "subClasses": null, "name": "complete remission", "body": "A remission which is characterized by a prolonged lack of all manifestations of a disease"}, {"id": "1369", "iri": "1369", "baseIri": "1369", "instances": "1369", "attributes": "1369", "label_IRI-based": "OGMS_0000121", "label_en": "partial remission", "annotations": {"definition": [{"identifier": "IAO_0000115", "language": "undefined", "value": "A remission which is characterized by a prolonged lack of some manifestations of a disease", "type": "label"}]}, "superClasses": ["643"], "subClasses": null, "name": "partial remission", "body": "A remission which is characterized by a prolonged lack of some manifestations of a disease"}]}, {"id": "652", "iri": "652", "baseIri": "652", "instances": "652", "attributes": "652", "label_IRI-based": "OGMS_0000118", "label_en": "onset", "annotations": {"curator note": [{"identifier": "IAO_0000232", "language": "undefined", "value": "creation date 2018-11-27", "type": "label"}], "definition": [{"identifier": "IAO_0000115", "language": "undefined", "value": "A disease stage that marks the beginning of a disease", "type": "label"}]}, "superClasses": ["382"], "subClasses": ["922"], "name": "onset", "body": "A disease stage that marks the beginning of a disease", "children": [{"id": "922", "iri": "922", "baseIri": "922", "instances": "922", "attributes": "922", "label_IRI-based": "OGMS_0000119", "label_en": "acute onset", "annotations": {"curator note": [{"identifier": "IAO_0000232", "language": "undefined", "value": "creation date 2018-11-27", "type": "label"}], "definition": [{"identifier": "IAO_0000115", "language": "undefined", "value": "A disease stage with a rapid unfolding of signs and symptoms", "type": "label"}]}, "superClasses": ["652"], "subClasses": null, "name": "acute onset", "body": "A disease stage with a rapid unfolding of signs and symptoms"}]}, {"id": "648", "iri": "648", "baseIri": "648", "instances": "648", "attributes": "648", "label_IRI-based": "OGMS_0000117", "label_en": "asymptomatic", "annotations": {"curator note": [{"identifier": "IAO_0000232", "language": "undefined", "value": "creation date: 2018-11-27", "type": "label"}], "definition": [{"identifier": "IAO_0000115", "language": "undefined", "value": "A disease stage characterized by the lack of symptoms associated with a given disease", "type": "label"}]}, "superClasses": ["382"], "subClasses": null, "name": "asymptomatic", "body": "A disease stage characterized by the lack of symptoms associated with a given disease"}, {"id": "574", "iri": "574", "baseIri": "574", "instances": "574", "attributes": "574", "label_IRI-based": "OGMS_0000133", "label_undefined": "progression stage", "annotations": null, "superClasses": ["382"], "subClasses": ["501"], "name": "progression stage", "body": "", "children": [{"id": "501", "iri": "501", "baseIri": "501", "instances": "501", "attributes": "501", "label_IRI-based": "OGMS_0000134", "label_undefined": "cancer progression stage", "annotations": null, "superClasses": ["574"], "subClasses": ["576", "578", "500", "503", "507"], "name": "cancer progression stage", "body": "", "children": [{"id": "576", "iri": "576", "baseIri": "576", "instances": "576", "attributes": "576", "label_IRI-based": "OGMS_0000135", "label_undefined": "cancer progression stage 0", "annotations": {"definition": [{"identifier": "IAO_0000115", "language": "undefined", "value": "A cancer progression stage characterized by abnormal cellular growth contained within normal tissue boundaries (e.g. carcinoma in situ).", "type": "label"}]}, "superClasses": ["501"], "subClasses": null, "name": "cancer progression stage 0", "body": "A cancer progression stage characterized by abnormal cellular growth contained within normal tissue boundaries (e.g. carcinoma in situ)."}, {"id": "578", "iri": "578", "baseIri": "578", "instances": "578", "attributes": "578", "label_IRI-based": "OGMS_0000136", "label_undefined": "cancer progression stage I", "annotations": {"definition": [{"identifier": "IAO_0000115", "language": "undefined", "value": "A cancer progression stage characterized by abnormal cellular growth that extends through normal local tissue boundaries as a contiguous mass.", "type": "label"}]}, "superClasses": ["501"], "subClasses": null, "name": "cancer progression stage I", "body": "A cancer progression stage characterized by abnormal cellular growth that extends through normal local tissue boundaries as a contiguous mass."}, {"id": "500", "iri": "500", "baseIri": "500", "instances": "500", "attributes": "500", "label_IRI-based": "OGMS_0000137", "label_undefined": "cancer progression stage II", "annotations": {"definition": [{"identifier": "IAO_0000115", "language": "undefined", "value": "A cancer progression stage characterized by abnormal cellular growth that extends well beyond normal local tissue boundaries as a contiguous mass.", "type": "label"}]}, "superClasses": ["501"], "subClasses": null, "name": "cancer progression stage II", "body": "A cancer progression stage characterized by abnormal cellular growth that extends well beyond normal local tissue boundaries as a contiguous mass."}, {"id": "503", "iri": "503", "baseIri": "503", "instances": "503", "attributes": "503", "label_IRI-based": "OGMS_0000138", "label_undefined": "cancer progression stage III", "annotations": {"definition": [{"identifier": "IAO_0000115", "language": "undefined", "value": "A cancer progression stage characterized by abnormal cellular growth that extends through normal local tissue boundaries as a contiguous mass and includes metastasis to one or more regional draining lymph nodes.", "type": "label"}]}, "superClasses": ["501"], "subClasses": null, "name": "cancer progression stage III", "body": "A cancer progression stage characterized by abnormal cellular growth that extends through normal local tissue boundaries as a contiguous mass and includes metastasis to one or more regional draining lymph nodes."}, {"id": "507", "iri": "507", "baseIri": "507", "instances": "507", "attributes": "507", "label_IRI-based": "OGMS_0000139", "label_undefined": "cancer progression stage IV", "annotations": {"definition": [{"identifier": "IAO_0000115", "language": "undefined", "value": "A cancer progression stage characterized by abnormal cellular growth that extends through normal local tissue boundaries as a contiguous mass and includes metastasis to other distant tissues besides lymph nodes.", "type": "label"}]}, "superClasses": ["501"], "subClasses": null, "name": "cancer progression stage IV", "body": "A cancer progression stage characterized by abnormal cellular growth that extends through normal local tissue boundaries as a contiguous mass and includes metastasis to other distant tissues besides lymph nodes."}]}]}]}